paramiko/__init__.py
paramiko/_version.py
paramiko/_winapi.py
paramiko/agent.py
paramiko/auth_handler.py
paramiko/auth_strategy.py
paramiko/ber.py
paramiko/buffered_pipe.py
paramiko/channel.py
paramiko/client.py
paramiko/common.py
paramiko/compress.py
paramiko/config.py
paramiko/dsskey.py
paramiko/ecdsakey.py
paramiko/ed25519key.py
paramiko/file.py
paramiko/hostkeys.py
paramiko/kex_curve25519.py
paramiko/kex_ecdh_nist.py
paramiko/kex_gex.py
paramiko/kex_group1.py
paramiko/kex_group14.py
paramiko/kex_group16.py
paramiko/kex_gss.py
paramiko/message.py
paramiko/packet.py
paramiko/pipe.py
paramiko/pkey.py
paramiko/primes.py
paramiko/proxy.py
paramiko/rsakey.py
paramiko/server.py
paramiko/sftp.py
paramiko/sftp_attr.py
paramiko/sftp_client.py
paramiko/sftp_file.py
paramiko/sftp_handle.py
paramiko/sftp_server.py
paramiko/sftp_si.py
paramiko/ssh_exception.py
paramiko/ssh_gss.py
paramiko/transport.py
paramiko/util.py
paramiko/win_openssh.py
paramiko/win_pageant.py
paramiko-3.4.1.dist-info/LICENSE
paramiko-3.4.1.dist-info/METADATA
paramiko-3.4.1.dist-info/WHEEL
paramiko-3.4.1.dist-info/top_level.txt
paramiko-3.4.1.dist-info/RECORD
