Metadata-Version: 2.1
Name: paramiko
Version: 3.4.1
Summary: SSH2 protocol library
Home-page: https://paramiko.org
Author: Jeff Forcier
Author-email: jeff@bitprophet.org
License: LGPL
Project-URL: Docs, https://docs.paramiko.org
Project-URL: Source, https://github.com/paramiko/paramiko
Project-URL: Issues, https://github.com/paramiko/paramiko/issues
Project-URL: Changelog, https://www.paramiko.org/changelog.html
Project-URL: CI, https://app.circleci.com/pipelines/github/paramiko/paramiko
Platform: Posix; MacOS X; Windows
Classifier: Development Status :: 5 - Production/Stable
Classifier: Intended Audience :: Developers
Classifier: License :: OSI Approved :: GNU Library or Lesser General Public License (LGPL)
Classifier: Operating System :: OS Independent
Classifier: Topic :: Internet
Classifier: Topic :: Security :: Cryptography
Classifier: Programming Language :: Python
Classifier: Programming Language :: Python :: 3
Classifier: Programming Language :: Python :: 3 :: Only
Classifier: Programming Language :: Python :: 3.6
Classifier: Programming Language :: Python :: 3.7
Classifier: Programming Language :: Python :: 3.8
Classifier: Programming Language :: Python :: 3.9
Classifier: Programming Language :: Python :: 3.10
Classifier: Programming Language :: Python :: 3.11
Requires-Python: >=3.6
Provides-Extra: gssapi
Provides-Extra: invoke
Provides-Extra: ed25519
Provides-Extra: all
